harness_ar_python/__init__.py
harness_ar_python/main.py
harness_ar_python-1.0.0.dist-info/LICENSE
harness_ar_python-1.0.0.dist-info/METADATA
harness_ar_python-1.0.0.dist-info/WHEEL
harness_ar_python-1.0.0.dist-info/top_level.txt
harness_ar_python-1.0.0.dist-info/RECORD
