Metadata-Version: 2.2
Name: harness-ar-python
Version: 1.0.0
Summary: Harness AR Python Package
Home-page: https://github.com/harness/harness-ar-python
Author: Arvind Choudary
Author-email: arvind.choudary@harness.io
Classifier: Programming Language :: Python :: 3
Classifier: License :: OSI Approved :: MIT License
Classifier: Operating System :: OS Independent
Requires-Python: >=3.6
License-File: LICENSE
Dynamic: author
Dynamic: author-email
Dynamic: classifier
Dynamic: description
Dynamic: description-content-type
Dynamic: home-page
Dynamic: requires-python
Dynamic: summary
